if_dsl_gui_ai/__init__.py
if_dsl_gui_ai/backyard.png
if_dsl_gui_ai/codeEditorFrame.py
if_dsl_gui_ai/dslClasses.py
if_dsl_gui_ai/entryway.png
if_dsl_gui_ai/gameFrame.py
if_dsl_gui_ai/gameInterpeter.py
if_dsl_gui_ai/gameWorldDSL.tx
if_dsl_gui_ai/gui.py
if_dsl_gui_ai/hallway.png
if_dsl_gui_ai/kitchen.png
if_dsl_gui_ai/main.py
if_dsl_gui_ai/noImg.png
if_dsl_gui_ai/old_requirements.txt
if_dsl_gui_ai/paintJeTata.png
if_dsl_gui_ai/pictureCreatorFrame.py
if_dsl_gui_ai/simpleGame.game
if_dsl_gui_ai/theEnd.jpg
if_dsl_gui_ai-0.1.2.dist-info/LICENSE
if_dsl_gui_ai-0.1.2.dist-info/METADATA
if_dsl_gui_ai-0.1.2.dist-info/WHEEL
if_dsl_gui_ai-0.1.2.dist-info/top_level.txt
if_dsl_gui_ai-0.1.2.dist-info/RECORD
